LICENSE
MANIFEST.in
README.md
setup.py
evident/__init__.py
evident/_exceptions.py
evident/citations.bib
evident/data_handler.py
evident/effect_size.py
evident/interactive.py
evident/plotting.py
evident/results.py
evident/stats.py
evident/utils.py
evident.egg-info/PKG-INFO
evident.egg-info/SOURCES.txt
evident.egg-info/dependency_links.txt
evident.egg-info/entry_points.txt
evident.egg-info/requires.txt
evident.egg-info/top_level.txt
evident/q2/__init__.py
evident/q2/_format.py
evident/q2/_methods.py
evident/q2/_transformer.py
evident/q2/_type.py
evident/q2/_visualizers.py
evident/q2/curve.css
evident/q2/dataframe.css
evident/q2/plugin_setup.py
evident/q2/tests/__init__.py
evident/q2/tests/test_plugin.py
evident/support_files/main.py
evident/support_files/templates/index.html
evident/tests/__init__.py
evident/tests/conftest.py
evident/tests/make_interactive.py
evident/tests/test_data_handler.py
evident/tests/test_effect_size.py
evident/tests/test_interactive.py
evident/tests/test_plotting.py
evident/tests/test_rm_anova.py
evident/tests/test_stats.py
evident/tests/test_utils.py
imgs/bokeh_panel_1.png
imgs/bokeh_panel_2.png
imgs/power_curve.png