Metadata-Version: 2.1
Name: evident
Version: 0.4.0
Summary: Effect size calculations for microbiome data.
Home-page: https://github.com/biocore/evident
Author: Gibraan Rahman
Author-email: grahman@eng.ucsd.edu
License: BSD-3-Clause
Platform: UNKNOWN
Classifier: Development Status :: 4 - Beta
Classifier: License :: OSI Approved :: BSD License
Classifier: Topic :: Software Development :: Libraries
Classifier: Topic :: Scientific/Engineering
Classifier: Topic :: Scientific/Engineering :: Bio-Informatics
Classifier: Programming Language :: Python :: 3
Classifier: Programming Language :: Python :: 3 :: Only
Classifier: Operating System :: Unix
Classifier: Operating System :: POSIX
Classifier: Operating System :: MacOS :: MacOS X
Provides-Extra: dev
